ZvolvArithmetic/__init__.py
ZvolvArithmetic/arithmetic_opertion.py
zvolvArithmeticz1-0.1.5.dist-info/LICENSE
zvolvArithmeticz1-0.1.5.dist-info/METADATA
zvolvArithmeticz1-0.1.5.dist-info/WHEEL
zvolvArithmeticz1-0.1.5.dist-info/top_level.txt
zvolvArithmeticz1-0.1.5.dist-info/RECORD
